tableauscraper/TableauScraper.py
tableauscraper/TableauWorkbook.py
tableauscraper/TableauWorksheet.py
tableauscraper/__init__.py
tableauscraper/api.py
tableauscraper/dashboard.py
tableauscraper/parameterControl.py
tableauscraper/selectItem.py
tableauscraper/utils.py
TableauScraper-0.1.29.dist-info/LICENSE
TableauScraper-0.1.29.dist-info/METADATA
TableauScraper-0.1.29.dist-info/WHEEL
TableauScraper-0.1.29.dist-info/top_level.txt
TableauScraper-0.1.29.dist-info/RECORD
