Metadata-Version: 2.1
Name: TableauScraper
Version: 0.1.29
Summary: Python library to scrape data from Tableau viz
Home-page: https://github.com/bertrandmartel/tableau-scraping
Author: Bertrand Martel
Author-email: bmartel.fr@gmail.com
License: MIT
Platform: UNKNOWN
Classifier: Programming Language :: Python
Classifier: Programming Language :: Python :: 3
Classifier: Programming Language :: Python :: 3.6
Classifier: Programming Language :: Python :: 3.7
Classifier: Programming Language :: Python :: 3.8
Classifier: Programming Language :: Python :: 3.9
Classifier: License :: OSI Approved :: MIT License
Classifier: Operating System :: OS Independent
Classifier: Topic :: Software Development
Requires-Python: >=3.6
License-File: LICENSE
Requires-Dist: beautifulsoup4 (>=4.0.0)
Requires-Dist: pandas
Requires-Dist: requests (>=2.14.0)
